pyhtml_htmx/__init__.py
pyhtml_htmx/htmx.py
pyhtml_htmx/py.typed
pyhtml_htmx-0.1.0.dist-info/licenses/LICENSE
pyhtml_htmx-0.1.0.dist-info/METADATA
pyhtml_htmx-0.1.0.dist-info/WHEEL
pyhtml_htmx-0.1.0.dist-info/top_level.txt
pyhtml_htmx-0.1.0.dist-info/RECORD
