Metadata-Version: 2.4
Name: pyhtml-htmx
Version: 0.1.0
Summary: HTMX integration for pyhtml - build dynamic HTML with HTMX attributes
Author: Ylan Allouche
License: MIT
Project-URL: homepage, https://github.com/YlanAllouche/pyhtml-htmx
Project-URL: repository, https://github.com/YlanAllouche/pyhtml-htmx
Project-URL: Bug Tracker, https://github.com/YlanAllouche/pyhtml-htmx/issues
Keywords: html,htmx,pyhtml,hypermedia
Classifier: Programming Language :: Python :: 3
Classifier: Intended Audience :: Developers
Classifier: Operating System :: OS Independent
Classifier: Development Status :: 3 - Alpha
Classifier: Topic :: Internet :: WWW/HTTP :: Dynamic Content
Classifier: Typing :: Typed
Requires-Python: >=3.10
License-File: LICENSE
Requires-Dist: pyhtml-enhanced>=2.2.4
Requires-Dist: typing-extensions>=4.12.2
Dynamic: license-file
